{
  "asymmetry": "Tory leader Kemi Badenoch claims 'lower council tax' pledge didn\u2019t mean people would pay less tax",
  "category": "wage_theft",
  "hook": "Tory leader Kemi Badenoch claims 'lower council tax' pledge ...",
  "core_fact": "Tory leader Kemi Badenoch claims 'lower council tax' pledge didn\u2019t mean people would pay less tax",
  "villain": "UK corporations",
  "share_trigger": "Did you see this? Tory leader Kemi Badenoch claims 'lower council tax' pledge didn\u2019t mean people w",
  "search_query": "Tory leader Kemi Badenoch claims 'lower council ta UK news 2026",
  "keywords": [
    "Tory",
    "leader",
    "Kemi",
    "Badenoch",
    "claims",
    "lower",
    "council",
    "pledge"
  ],
  "estimated_anger_score": 193,
  "timestamp": "2026-03-24T13:30:00.769497",
  "slot": 4,
  "findings_count": 470
}